[
  {
    "date": {
      "fullDate": "13.07.2005 18:56",
      "date": "13.07.2005",
      "time": "18:56"
    },
    "id": "#10395",
    "content": [
      {
        "username": "jcm",
        "message": "misst mal bei Fridolin den Intelligenzquotienten...."
      },
      {
        "username": "@jeedi",
        "message": "jcm: miss lieber seine temperatur, da kriegste zumindest zweistellige werte.."
      },
      {
        "message": "\n"
      }
    ]
  },
  {
    "date": {
      "fullDate": "13.07.2005 22:04",
      "date": "13.07.2005",
      "time": "22:04"
    },
    "id": "#10335",
    "content": [
      {
        "username": "Highscore",
        "message": "chuckafucka??"
      },
      {
        "username": "pLaGue",
        "message": "einer meiner letzten verbleibenden rl freunde!"
      },
      {
        "username": "pLaGue",
        "message": ";D"
      },
      {
        "username": "_biO_",
        "message": "mal fragen wie er das sieht"
      }
    ]
  },
  {
    "date": {
      "fullDate": "13.07.2005 22:05",
      "date": "13.07.2005",
      "time": "22:05"
    },
    "id": "#10337",
    "content": [
      {
        "message": "meadmb: eigentlich sieht sie ja ziemlich geil aus ^^"
      },
      {
        "message": "\nKevin: nur sie müsste ein wenig mehr lächeln"
      },
      {
        "message": "\nmeadmb: jo und weniger anhaben"
      },
      {
        "message": "\nKevin: am besten gar nix^^"
      },
      {
        "message": "\nmeadmb: dann müsste sie auch nicht mehr lächeln :D"
      }
    ]
  },
  {
    "date": {
      "fullDate": "13.07.2005 22:06",
      "date": "13.07.2005",
      "time": "22:06"
    },
    "id": "#10338",
    "content": [
      {
        "message": "(Astenia`Unica) moin, hat wer nen dl link fürn patch ?"
      },
      {
        "message": "\n(DLGEHTNICHT) &lt;---"
      },
      {
        "message": "\n(Astenia`Unica) darf man haben ? :)"
      },
      {
        "message": "\n(DLGEHTNICHT) &lt;&lt;&lt;=== !!!"
      },
      {
        "message": "\n(Firehawk) tjo manche raffens fast"
      }
    ]
  },
  {
    "date": {
      "fullDate": "13.07.2005 22:09",
      "date": "13.07.2005",
      "time": "22:09"
    },
    "id": "#10402",
    "content": [
      {
        "username": "renbolicious```",
        "message": "q@cserve.quakenet.org auth renbo redlabel7 "
      },
      {
        "username": "`4star|Kysusbka",
        "message": "k "
      },
      {
        "username": "renbolicious```",
        "message": "so ein käse "
      },
      {
        "username": "renbolicious```",
        "message": "anstatt msg amsg gemacht :D "
      },
      {
        "username": "renbolicious```",
        "message": "ich geh kaputt "
      }
    ]
  },
  {
    "date": {
      "fullDate": "13.07.2005 22:10",
      "date": "13.07.2005",
      "time": "22:10"
    },
    "id": "#10408",
    "content": [
      {
        "username": "DeadEye",
        "message": "lol... mein vater kommt zu mir und meint: \"hast mitbekommen, der kerl der sasser programmiert hat hat 1 jahr und 9 monate auf bewährung bekommen, weil er weltweit computer zum absturz gebracht hat. wie lang müsste dann erst bill gates bekommen?\""
      },
      {
        "username": "DeadEye",
        "message": "und als er rausging noch: \"5mal lebenslänglich wäre noch zu wenig\""
      }
    ]
  },
  {
    "date": {
      "fullDate": "13.07.2005 22:13",
      "date": "13.07.2005",
      "time": "22:13"
    },
    "id": "#10414",
    "content": [
      {
        "message": "(+Qui-Gon) burn77"
      },
      {
        "message": "\n(+Qui-Gon) du bist FAST den ganzen tag hier...wie verdienst du dein Geld?"
      },
      {
        "message": "\n(@burn77) ich filme mein arsch 24h"
      }
    ]
  },
  {
    "date": {
      "fullDate": "13.07.2005 22:16",
      "date": "13.07.2005",
      "time": "22:16"
    },
    "id": "#10415",
    "content": [
      {
        "username": "DerCorny",
        "message": "elena, du _nervst_. STFU, k?"
      },
      {
        "username": "Elena",
        "message": "ach komm schon"
      },
      {
        "username": "DerCorny",
        "message": "boah ich meins ernst. ich hab kein bock"
      },
      {
        "username": "Elena",
        "message": "och duuuuu - kann doch ganich!"
      },
      {
        "username": "DerCorny",
        "message": "biatch, hör zu: schreibste noch *irgendwas* zu diesem thema und es gibt kickban"
      },
      {
        "username": "zu",
        "message": "diesem thema und es gibt kickban"
      },
      {
        "username": "Elena",
        "message": "brb, muss mal telefonieren..."
      },
      {
        "username": "DerCorny",
        "message": "na wunderbar, endlich ruhe. ausnahmsweise hat deren telefoniererei mal was gutes"
      },
      {
        "username": "DerCorny",
        "message": "boah, ich brauch erstmal nen nachschub kaffee bei dem stress"
      },
      {
        "username": "Hedikins",
        "message": "hehe"
      },
      {
        "username": "DerCorny",
        "message": "ich glaub jetzt knallts!"
      },
      {
        "username": "DerCorny",
        "message": "sets mode +b *!*redflower@*.dip0.t-ipconnect.de"
      },
      {
        "username": "Elena",
        "message": "has been kicked by DerCorny (DerCorny)"
      },
      {
        "username": "Hedikins",
        "message": "wtf?"
      },
      {
        "username": "Hedikins",
        "message": "was solllte denn das? sie war doch völlig ruhig?"
      },
      {
        "username": "DerCorny",
        "message": "so? dann rate mal bei wem gerade das telefon klingelt"
      }
    ]
  },
  {
    "date": {
      "fullDate": "14.07.2005 19:40",
      "date": "14.07.2005",
      "time": "19:40"
    },
    "id": "#10427",
    "content": [
      {
        "username": "november",
        "message": "englisch, latein, spanisch ranzösisch, finnisch... aber kein türkisch"
      },
      {
        "username": "november",
        "message": ":/"
      },
      {
        "username": "Google",
        "message": "ranzösisch?"
      },
      {
        "username": "Pirx",
        "message": "Ranzösisch?"
      },
      {
        "username": "Google",
        "message": "ranzösch hört sich die sprache in meinen ohren auch an"
      },
      {
        "username": "november",
        "message": "ja RANZösisch ;)"
      },
      {
        "username": "Pirx",
        "message": "Aris, die wunderbare Hauptstadt der Ranzosen"
      },
      {
        "username": "Pirx",
        "message": "mit dem berühmten Iffelturm"
      },
      {
        "username": "november",
        "message": "lecker Aguette gibts da"
      },
      {
        "username": "Zw0",
        "message": "das And der Iebe, oder wie war das?"
      }
    ]
  },
  {
    "date": {
      "fullDate": "14.07.2005 19:46",
      "date": "14.07.2005",
      "time": "19:46"
    },
    "id": "#10445",
    "content": [
      {
        "username": "november",
        "message": "oh man ich liebe oliver geissen"
      },
      {
        "username": "november",
        "message": "ich sitz in boxers und feinripp vorm rechner"
      },
      {
        "username": "DefJam",
        "message": "pfui"
      },
      {
        "username": "ratm",
        "message": "... o_O?"
      },
      {
        "username": "november",
        "message": "es ist mitten inner nacht"
      },
      {
        "username": "november",
        "message": "ich denk mir \"asozialer geht nich\""
      },
      {
        "username": "november",
        "message": "dann guck ich oli geissen"
      },
      {
        "username": "november",
        "message": "und meine welt ist wieder in ordnung und ich weiss ich gehör zu elite"
      }
    ]
  },
  {
    "date": {
      "fullDate": "14.07.2005 19:46",
      "date": "14.07.2005",
      "time": "19:46"
    },
    "id": "#10446",
    "content": [
      {
        "message": "Hellfire-Torrod: was is beim lüfter eigendlich besser, pusten oder saugen?"
      },
      {
        "message": "\nGertz: saugend"
      },
      {
        "message": "\nGertz: geht dir doch auch besser wenn nen weib saugt... anstatt pustet XD"
      },
      {
        "message": "\nHellfire-Torrod: klasse erklärung!"
      },
      {
        "message": "\nHellfire-Torrod: warum solls den pc auch schlechter gehen als mir ..."
      },
      {
        "message": "\n"
      }
    ]
  },
  {
    "date": {
      "fullDate": "14.07.2005 19:51",
      "date": "14.07.2005",
      "time": "19:51"
    },
    "id": "#10450",
    "content": [
      {
        "username": "bueffli",
        "message": "fuck hee"
      },
      {
        "username": "bueffli",
        "message": "ich hab ends die riesen quaddel am arm, mivh hat irgendwas gestochen :("
      },
      {
        "username": "bueffli",
        "message": "hoffe da war noch soviel amphe in meinem blut dass das Vieh gegen die Wand saust und zerschellt!"
      }
    ]
  },
  {
    "date": {
      "fullDate": "14.07.2005 19:51",
      "date": "14.07.2005",
      "time": "19:51"
    },
    "id": "#10451",
    "content": [
      {
        "username": "@chris`oelt",
        "message": "rektal is garkein thema"
      },
      {
        "username": "@chris`oelt",
        "message": "da bin ich offen fuer alles"
      }
    ]
  },
  {
    "date": {
      "fullDate": "14.07.2005 19:53",
      "date": "14.07.2005",
      "time": "19:53"
    },
    "id": "#10456",
    "content": [
      {
        "username": "@dflv|silium",
        "message": "hey wie willste denn den tag überstehen ohne morgens zu kiffen???"
      },
      {
        "username": "+dflv|thySEus",
        "message": "gar nicht erst aufstehen"
      }
    ]
  },
  {
    "date": {
      "fullDate": "14.07.2005 20:01",
      "date": "14.07.2005",
      "time": "20:01"
    },
    "id": "#10483",
    "content": [
      {
        "username": "TheDarkSide",
        "message": "Is zwar nur nen Zergdackel, aber was für einer"
      },
      {
        "username": "Imago",
        "message": "hehe Zergdackel?"
      },
      {
        "username": "Imago",
        "message": "zuviel Starcraft gespielt?"
      }
    ]
  },
  {
    "date": {
      "fullDate": "14.07.2005 21:09",
      "date": "14.07.2005",
      "time": "21:09"
    },
    "id": "#10508",
    "content": [
      {
        "username": "Capt_Matthias",
        "message": "Rektalthermometer"
      },
      {
        "username": "Capt_Matthias",
        "message": "Falls du heute mal wieder einen dieser \"Ich hasse meinen Job\" - Tage hast, versuche es mal damit: "
      },
      {
        "username": "Capt_Matthias",
        "message": "Gehe nach Feierabend in eine Apotheke und gehe zu den Fieberthermometern. Kaufe ein Rektalthermometer der Marke \"Johnson &amp; Johnson\". Versichere dich, dass es dieser Hersteller ist! "
      },
      {
        "username": "Capt_Matthias",
        "message": "Wenn du zu Hause bist, schließe deine Türen ab, stecke dein Telefon aus und stelle die Klingel ab. Du darfst nicht gestört werden! Ziehe dir bequeme Kleidung an und mache es dir in deinem Bett so richtig gemütlich."
      },
      {
        "username": "Capt_Matthias",
        "message": "Jetzt öffne die Packung und nehme das Rektalthermometer zur Hand. Lege es vorsichtig neben dir auf das Bett, so dass es nicht beschädigt wird."
      },
      {
        "username": "Capt_Matthias",
        "message": "Nehme nun die Packungsbeilage aus der Verpackung und lese sie dir durch.. Du wirst auf den folgenden Satz stoßen: Jedes Rektalthermometer der Marke Johnson &amp; Johnson\" ist persönlich getestet.\""
      },
      {
        "username": "Capt_Matthias",
        "message": "Nun schließe deine Augen und wiederhole diesen Satz fünf mal laut: \"Ich bin so glücklich, dass ich nicht in der Qualitätskontrolle bei der Firma \"Johnson &amp; Johnson\" arbeite!!\"."
      },
      {
        "username": "Capt_Matthias",
        "message": "Merke:"
      },
      {
        "username": "Capt_Matthias",
        "message": "Es gibt immer irgendwo jemanden, mit einem schlechteren Job als Deinen!"
      }
    ]
  },
  {
    "date": {
      "fullDate": "15.07.2005 00:20",
      "date": "15.07.2005",
      "time": "00:20"
    },
    "id": "#10526",
    "content": [
      {
        "username": "pnx`",
        "message": "wieso rebootest du denn staendig"
      },
      {
        "username": "idiana",
        "message": "weil er einen nippel auf den reset knopf gemalt hat"
      },
      {
        "message": "\n"
      }
    ]
  },
  {
    "date": {
      "fullDate": "15.07.2005 00:42",
      "date": "15.07.2005",
      "time": "00:42"
    },
    "id": "#10529",
    "content": [
      {
        "username": "mahorca",
        "message": "wieso kann man beim bringdienst nicht mit karte bezahlen? was hat das für einen sinn für faule menschen wenn sie erst auf der sparkasse geld abheben müssen??"
      }
    ]
  },
  {
    "date": {
      "fullDate": "15.07.2005 00:42",
      "date": "15.07.2005",
      "time": "00:42"
    },
    "id": "#10531",
    "content": [
      {
        "username": "checker777",
        "message": "wählst du die CDU???"
      },
      {
        "username": "JoeBananas",
        "message": "was ich wähle"
      },
      {
        "username": "JoeBananas",
        "message": "geht nur mich was an :D"
      },
      {
        "username": "checker777",
        "message": "nein stimmt doch gar nicht."
      },
      {
        "username": "JoeBananas",
        "message": "wobei, dass ich operator im CDU Channel bin, könnte schon verdächtig sein merke ich gerade"
      },
      {
        "username": "checker777",
        "message": "hehe..^"
      }
    ]
  },
  {
    "date": {
      "fullDate": "15.07.2005 15:21",
      "date": "15.07.2005",
      "time": "15:21"
    },
    "id": "#10578",
    "content": [
      {
        "username": "BK",
        "message": "deine freundin muss dich lieben"
      },
      {
        "username": "nostrow",
        "message": "nein, aber sie braucht das visum"
      }
    ]
  }
]