[
  {
    "date": {
      "fullDate": "19.08.2005 13:53",
      "date": "19.08.2005",
      "time": "13:53"
    },
    "id": "#14514",
    "content": [
      {
        "type": "message",
        "username": "@srv|email",
        "message": "War irgendwie n langer Abend."
      },
      {
        "type": "message",
        "username": "@srv|email",
        "message": "Bis zum Kreisel dachte ich aber, ich wäre schon wieder fit genug, um Auto zu fahren."
      },
      {
        "type": "message",
        "username": "@srv|email",
        "message": "Dann hält so ein Fahrradfahrer vor mir den Arm raus und fährt aus dem Kreisel."
      },
      {
        "type": "message",
        "username": "@srv|email",
        "message": "Was mach ich? Anstatt zu blinken, halt ich im Auto den Arm nach rechts und fahre hinterher -_-"
      }
    ]
  },
  {
    "date": {
      "fullDate": "19.08.2005 14:08",
      "date": "19.08.2005",
      "time": "14:08"
    },
    "id": "#14563",
    "content": [
      {
        "type": "misc",
        "text": "(+da2kirby) mach mal //say $ip"
      },
      {
        "type": "misc",
        "text": "\n(+da2kirby) dann kann ich dir deinen wohnort sagen"
      },
      {
        "type": "misc",
        "text": "\n(![BooM]) brauch ich nicht"
      },
      {
        "type": "misc",
        "text": "\n(![BooM]) ich weiss wo ich wohne"
      }
    ]
  },
  {
    "date": {
      "fullDate": "19.08.2005 14:16",
      "date": "19.08.2005",
      "time": "14:16"
    },
    "id": "#14578",
    "content": [
      {
        "type": "message",
        "username": "Treibholz",
        "message": "und Sprechgesang muss kein HipHop sein, sonst wäre der Papst ja Rapper!"
      },
      {
        "type": "message",
        "username": "Treibholz",
        "message": "wobei...."
      },
      {
        "type": "message",
        "username": "Treibholz",
        "message": "der hat auch immer so weite Klamotten an..."
      },
      {
        "type": "message",
        "username": "Treibholz",
        "message": "und fette Ketten..."
      }
    ]
  },
  {
    "date": {
      "fullDate": "19.08.2005 16:57",
      "date": "19.08.2005",
      "time": "16:57"
    },
    "id": "#14655",
    "content": [
      {
        "type": "message",
        "username": "Meterchen",
        "message": "Ich habe jetzt auch DSL, wie komme ich in so einen esports Club?"
      },
      {
        "type": "message",
        "username": "R!oT",
        "message": "Auf nem Public-Server die Clanmembers fragen oder das Join Us Formular auf der Clanpage ausfüllen... etc."
      },
      {
        "type": "message",
        "username": "R!oT",
        "message": "Es gibt so viel Möglichkeiten..."
      },
      {
        "type": "message",
        "username": "Meterchen",
        "message": "Kann ich nicht bei euch anfangen?"
      },
      {
        "type": "message",
        "username": "R!oT",
        "message": "Wenn du keine Spielerfahrung hast und nichts triffst dann nicht. ^^"
      },
      {
        "type": "message",
        "username": "Meterchen",
        "message": "Oder wenigstens ein Testspiel machen?"
      },
      {
        "type": "message",
        "username": "R!oT",
        "message": "Ja OK."
      },
      {
        "type": "message",
        "username": "Meterchen",
        "message": "Gut, dann muss ich mir jetzt nur noch das Spiel kaufen..."
      },
      {
        "type": "message",
        "username": "R!oT",
        "message": "OMFG..."
      }
    ]
  },
  {
    "date": {
      "fullDate": "19.08.2005 17:25",
      "date": "19.08.2005",
      "time": "17:25"
    },
    "id": "#14637",
    "content": [
      {
        "type": "message",
        "username": "lommes|afk",
        "message": "ich find des ok"
      },
      {
        "type": "message",
        "username": "lommes|afk",
        "message": "und wenn meine frau später mal nich zu hause bleiben will hab ich keine probleme damit an ihrer stelle mich um die kinder zu kümmern"
      },
      {
        "type": "message",
        "username": "lommes|afk",
        "message": "vorrausgesetzt natürlich die kinder sind volljährig und wohnen auswärts ^^"
      }
    ]
  },
  {
    "date": {
      "fullDate": "20.08.2005 10:26",
      "date": "20.08.2005",
      "time": "10:26"
    },
    "id": "#14648",
    "content": [
      {
        "type": "message",
        "username": "Chaos|krieger",
        "message": "oder bringste selbst ne 3-4 meter leiter mit?"
      },
      {
        "type": "message",
        "username": "Chaos|krieger",
        "message": "bzw. glaube das sind mehr.. ka"
      },
      {
        "type": "message",
        "username": "Chaos|krieger",
        "message": "2 stockwerke"
      },
      {
        "type": "message",
        "username": "Chaos|krieger",
        "message": "ich weis nur noch nicht so ganz was ich den eltern meiner freundin sagen soll"
      },
      {
        "type": "message",
        "username": "Chaos|krieger",
        "message": "wie ich ins haus kam"
      },
      {
        "type": "message",
        "username": "Chaos|krieger",
        "message": "die wissen das ich kein schlüssel dabei hatte"
      },
      {
        "type": "message",
        "username": "shad0w",
        "message": "tzz"
      },
      {
        "type": "message",
        "username": "Chaos|krieger",
        "message": "\"20 jahre frankfurt, ich brauch kein schlüssel\"?"
      }
    ]
  },
  {
    "date": {
      "fullDate": "20.08.2005 10:26",
      "date": "20.08.2005",
      "time": "10:26"
    },
    "id": "#14652",
    "content": [
      {
        "type": "message",
        "username": "Komakalle",
        "message": "oh gott"
      },
      {
        "type": "message",
        "username": "Komakalle",
        "message": "meine mutter regt  sich auf"
      },
      {
        "type": "message",
        "username": "Komakalle",
        "message": "weil sie immer sagt dass ich und mein vatter nich alleine klar kommen"
      },
      {
        "type": "message",
        "username": "Foley",
        "message": "habt ihr was angestellt?"
      },
      {
        "type": "message",
        "username": "Komakalle",
        "message": "dann war sie mal eine woche weg und alles lief super"
      },
      {
        "type": "message",
        "username": "Komakalle",
        "message": "und die regt sich auf weil wir sie nich brauchen"
      },
      {
        "type": "message",
        "username": "Foley",
        "message": "lol"
      },
      {
        "type": "message",
        "username": "Foley",
        "message": "kenn ich"
      }
    ]
  },
  {
    "date": {
      "fullDate": "20.08.2005 10:34",
      "date": "20.08.2005",
      "time": "10:34"
    },
    "id": "#14677",
    "content": [
      {
        "type": "message",
        "username": "Gast418",
        "message": "... hat mir jemand einen Euro über Paypal ?? Ich habe nur so ein schwules Jugendsparkonto und kann nichts an Paypal überweisen. Kann mir jemanf helfen ??"
      },
      {
        "type": "message",
        "username": "Meko",
        "message": "modernes betteln"
      },
      {
        "type": "message",
        "username": "Meko",
        "message": "wie geil"
      },
      {
        "type": "message",
        "username": "d00p",
        "message": "ich glaub irgendwo hörts uff"
      },
      {
        "type": "message",
        "username": "d00p",
        "message": "LOL"
      },
      {
        "type": "message",
        "username": "Meko",
        "message": "is hier ne fussgängerzone oder wie? ^^"
      },
      {
        "type": "message",
        "username": "Gast418",
        "message": "... is ja nur 1 Euro ..."
      },
      {
        "type": "message",
        "username": "Meko",
        "message": "der spruch kommt da auch immer :p"
      },
      {
        "type": "misc",
        "text": "\n"
      }
    ]
  },
  {
    "date": {
      "fullDate": "20.08.2005 10:40",
      "date": "20.08.2005",
      "time": "10:40"
    },
    "id": "#14667",
    "content": [
      {
        "type": "message",
        "username": "thomas001",
        "message": "[euirc] -!- thomas001|badminton Erroneous Nickname: Reserved for IRCops"
      },
      {
        "type": "message",
        "username": "thomas001",
        "message": "aeh?"
      }
    ]
  },
  {
    "date": {
      "fullDate": "20.08.2005 10:46",
      "date": "20.08.2005",
      "time": "10:46"
    },
    "id": "#14696",
    "content": [
      {
        "type": "message",
        "username": "TRF415",
        "message": "mach weiter"
      },
      {
        "type": "message",
        "username": "katze",
        "message": "fg"
      },
      {
        "type": "message",
        "username": "TRF415",
        "message": "saftsack + wort"
      },
      {
        "type": "message",
        "username": "TRF415",
        "message": "^^"
      },
      {
        "type": "message",
        "username": "katze",
        "message": "saftsackpresser"
      },
      {
        "type": "message",
        "username": "TRF415",
        "message": "mal schauen wie weit wir kommen"
      },
      {
        "type": "message",
        "username": "TRF415",
        "message": "saftsackpressermaschine"
      },
      {
        "type": "message",
        "username": "katze",
        "message": "saftsackpressermaschinenputzer"
      },
      {
        "type": "message",
        "username": "TRF415",
        "message": "oje...."
      },
      {
        "type": "message",
        "username": "cala",
        "message": "saftsackpressermaschinenputzlappeningenieurslampereinigungsbatteriewechsel"
      },
      {
        "type": "misc",
        "text": "\nakkuschrauberadaptersteckdosenverlängerrungsschnurentwirrungsexpertenfamiliekleidungsherstellungsfirma"
      },
      {
        "type": "misc",
        "text": "\nwartungshelferkundenbetreuungszimmerreinigungkraftexpertenteamgesellschaftslogo"
      },
      {
        "type": "misc",
        "text": "\ninformationsassistentsgemeinschaftsaktionsverrat"
      },
      {
        "type": "message",
        "username": "cala",
        "message": "lool .."
      },
      {
        "type": "message",
        "username": "Alexander",
        "message": "omg.."
      },
      {
        "type": "message",
        "username": "cH40z-Lord",
        "message": "omfg ?"
      }
    ]
  },
  {
    "date": {
      "fullDate": "20.08.2005 15:42",
      "date": "20.08.2005",
      "time": "15:42"
    },
    "id": "#14744",
    "content": [
      {
        "type": "message",
        "username": "Kanzler",
        "message": "Nein, nur die eine hat einen Freund, die andere war solo, und ich hatte auch ne Beziehung am laufen."
      },
      {
        "type": "message",
        "username": "cerb",
        "message": "war das die Beziehung bei der sich dann der andere Freund mal meldete ? ;)"
      },
      {
        "type": "message",
        "username": "Kanzler",
        "message": "cerb, ich war mit der schon eine Woche vorher im Bett, und Montags hat sich in der Schule dann ihr Freund gemeldet... Quer durch die volle Pausenhalle... \"DU WARST MIT MEINER FREUNDIN IM BETT???\""
      },
      {
        "type": "message",
        "username": "Kanzler",
        "message": "Ich darauf: \"jo, war ich.\" Er sagte dann nur,\"Hmm, ihr scheint die Nacht ja gut Spaß gehabt zu haben. Ich wollte jetzt nach Hause fahren, soll ich dich nmitnehmen?\""
      }
    ]
  },
  {
    "date": {
      "fullDate": "20.08.2005 17:54",
      "date": "20.08.2005",
      "time": "17:54"
    },
    "id": "#14753",
    "content": [
      {
        "type": "message",
        "username": "Mephisto",
        "message": "Am geilsten war die kathi :D"
      },
      {
        "type": "message",
        "username": "Mephisto",
        "message": "Macht da im Dunkeln mit so nem Kerl rum, sieht den im Licht und geht sofort von dem weg. :D"
      },
      {
        "type": "message",
        "username": "Déagol",
        "message": "rofl"
      }
    ]
  },
  {
    "date": {
      "fullDate": "21.08.2005 11:25",
      "date": "21.08.2005",
      "time": "11:25"
    },
    "id": "#14737",
    "content": [
      {
        "type": "message",
        "username": "Rioter",
        "message": "ich hasse die WELT!!!!!!!!!! 0.5Terrabyte speciher @ festplatte im Raid betrieb 1024 MB dualchannel 128 bit speicher, neue 1600 dpimaus,precision gaming headset und ich komm nicht weiter weil mir ein uraltes diskettenlaufwerk fehlt..."
      }
    ]
  },
  {
    "date": {
      "fullDate": "21.08.2005 11:27",
      "date": "21.08.2005",
      "time": "11:27"
    },
    "id": "#14747",
    "content": [
      {
        "type": "message",
        "username": "Alucard|Futtern",
        "message": "schon komisch... 2 eier reichen aus um so viele frauen zu beglücken... aber manchmal reichen 3 eier einfach nicht um satt zu werden..."
      }
    ]
  },
  {
    "date": {
      "fullDate": "21.08.2005 13:46",
      "date": "21.08.2005",
      "time": "13:46"
    },
    "id": "#14838",
    "content": [
      {
        "type": "message",
        "username": "Dosenthunfisch",
        "message": "aaaaah... ich werde von pornowerbung terrorisiert..."
      },
      {
        "type": "message",
        "username": "intelinsider",
        "message": "ieh ein ie nutzer"
      }
    ]
  },
  {
    "date": {
      "fullDate": "21.08.2005 14:09",
      "date": "21.08.2005",
      "time": "14:09"
    },
    "id": "#14788",
    "content": [
      {
        "type": "message",
        "username": "yusufaslan",
        "message": "hi wer will mit mir chatten ich bin 15"
      },
      {
        "type": "message",
        "username": "panique",
        "message": "rofl"
      },
      {
        "type": "message",
        "username": "panique",
        "message": "das ist wie \"wer will mich küssen, ich hab herpes\""
      }
    ]
  },
  {
    "date": {
      "fullDate": "21.08.2005 15:46",
      "date": "21.08.2005",
      "time": "15:46"
    },
    "id": "#14797",
    "content": [
      {
        "type": "message",
        "username": "StaTiC",
        "message": "ich hab nen plüschtiger aufm jahrmarkt gewonnen danach ist mir aber erst eingefallen das ich keine freundin hab"
      }
    ]
  },
  {
    "date": {
      "fullDate": "21.08.2005 16:21",
      "date": "21.08.2005",
      "time": "16:21"
    },
    "id": "#14852",
    "content": [
      {
        "type": "message",
        "username": "Löwiatz",
        "message": "boa ich wieg jetzt 60 km..."
      },
      {
        "type": "message",
        "username": "trasher",
        "message": "ja du ich würd wenn ich du wäre 2m abnehmen!"
      },
      {
        "type": "message",
        "username": "sickxhero",
        "message": "kann mir das jemand in minuten umrechnen das ich das auch endlich mal verstehe?"
      }
    ]
  },
  {
    "date": {
      "fullDate": "21.08.2005 16:29",
      "date": "21.08.2005",
      "time": "16:29"
    },
    "id": "#14809",
    "content": [
      {
        "type": "message",
        "username": "coaxspi",
        "message": "ich hab das gemacht: Ich geh zu ihr und frag so \"Würdest du dir Schuhe kaufen wenn du keine Beine hättest?\" Sie: \"Äh... nein wieso?\" Ich:\"Warum kaufste dir dann nen BH??\" ... da hats klatsch gemacht xD"
      }
    ]
  },
  {
    "date": {
      "fullDate": "21.08.2005 17:00",
      "date": "21.08.2005",
      "time": "17:00"
    },
    "id": "#14830",
    "content": [
      {
        "type": "message",
        "username": "Brot",
        "message": "dank einem beschissenen ksc fan, der einen \"ich bin im urlaub auto responder\" so konfoguriert hat, dass er bei jeder mail von der mailingliste in die mailingliste antwortet, was zu einer klitzekleinen kettenreaktion gefuehrt hat, habe ich jetzt 588 neue mails"
      }
    ]
  }
]