[
  {
    "date": {
      "fullDate": "21.05.2006 12:05",
      "date": "21.05.2006",
      "time": "12:05"
    },
    "id": "#42424",
    "content": [
      {
        "type": "message",
        "username": "pig`afk",
        "message": "mein mitbewohner will ne ebay seite speichern"
      },
      {
        "type": "message",
        "username": "pig`afk",
        "message": "aber das geht irgendwie nicht"
      },
      {
        "type": "message",
        "username": "pig`afk",
        "message": "übertragungsfehler"
      },
      {
        "type": "message",
        "username": "pig`afk",
        "message": "ich soll mir das anguggn weil er internet DAU ist"
      },
      {
        "type": "message",
        "username": "pig`afk",
        "message": "ich gucke finde den fehler nicht"
      },
      {
        "type": "message",
        "username": "pig`afk",
        "message": "weil auch dau"
      },
      {
        "type": "message",
        "username": "pig`afk",
        "message": "will prüfen ob der pc die seite jedenfalls teilweise speichert"
      },
      {
        "type": "message",
        "username": "pig`afk",
        "message": "klicke alle ordner durch"
      },
      {
        "type": "message",
        "username": "pig`afk",
        "message": "man muss dazu folgendes wissen"
      },
      {
        "type": "message",
        "username": "pig`afk",
        "message": "sein icq ist an seine freundin ist online"
      },
      {
        "type": "message",
        "username": "pig`afk",
        "message": "sein handy liegt neben dem laptop und seine freundin ist dran. das handy ist auf laut gesstellt"
      },
      {
        "type": "message",
        "username": "pig`afk",
        "message": "ich und er flachsen mit ihr ein wenig rum während ich am laptop klicke"
      },
      {
        "type": "message",
        "username": "pig`afk",
        "message": "und"
      },
      {
        "type": "message",
        "username": "pig`afk",
        "message": "alle seine ordner ansichten sind auf vorschau eingestellt"
      },
      {
        "type": "message",
        "username": "pig`afk",
        "message": "so ich suche also den ordner in dem er angeblich die seite speichern sollte"
      },
      {
        "type": "message",
        "username": "pig`afk",
        "message": "der befindet sich in einem unterordner tief drin der 'schatz' heisst"
      },
      {
        "type": "message",
        "username": "pig`afk",
        "message": "ich klicke mich zurück und mit einem mal hakt die laptopmaus"
      },
      {
        "type": "message",
        "username": "pig`afk",
        "message": "also habe ich den hauptordner 'schatz' mit der vorschau der inhalte"
      },
      {
        "type": "message",
        "username": "pig`afk",
        "message": "auf einem foto sieht mal ein wenig haut und was weisses"
      },
      {
        "type": "message",
        "username": "pig`afk",
        "message": "mit einem mal weiten sich meine augen"
      },
      {
        "type": "message",
        "username": "pig`afk",
        "message": "und ich sage SEHR laut"
      },
      {
        "type": "message",
        "username": "pig`afk",
        "message": "'L O L?! IS DAS IHRE MUSCHI???'"
      },
      {
        "type": "message",
        "username": "pig`afk",
        "message": "in dem moment realisiere ich"
      },
      {
        "type": "message",
        "username": "pig`afk",
        "message": "dass das handy neben dem laptop liegt"
      },
      {
        "type": "message",
        "username": "pig`afk",
        "message": "mein mitbewohner hat in dem moment aufgehört zu atmen"
      },
      {
        "type": "message",
        "username": "pig`afk",
        "message": "2 sekunden später blinkt icq"
      },
      {
        "type": "message",
        "username": "pig`afk",
        "message": "message von ihr"
      },
      {
        "type": "message",
        "username": "pig`afk",
        "message": "'du bist tot.'"
      },
      {
        "type": "message",
        "username": "pig`afk",
        "message": "das bescheuerte an der tatsache ist, dass ich erst dachte auf dem foto ist ein hamster"
      },
      {
        "type": "message",
        "username": "pig`afk",
        "message": "keine ahnung warum"
      },
      {
        "type": "message",
        "username": "pig`afk",
        "message": "naja wie dem auch sei ich habe es immerhin geschafft die dämliche seite zu speichern"
      }
    ]
  },
  {
    "date": {
      "fullDate": "21.05.2006 22:40",
      "date": "21.05.2006",
      "time": "22:40"
    },
    "id": "#42632",
    "content": [
      {
        "type": "message",
        "username": "Shadow|alt_und_schrumplig",
        "message": "daran merkte ich gestern, dass ich zuviel wow zocke.. dachte so \"hey morgen hast geburtstach. Dein 22ter\" und fürn Bruchteil einer sekunde \"22 = grade; grade = neue Zauber und Fähigkeiten beim Lehrmeister\""
      }
    ]
  },
  {
    "date": {
      "fullDate": "22.05.2006 01:48",
      "date": "22.05.2006",
      "time": "01:48"
    },
    "id": "#42652",
    "content": [
      {
        "type": "message",
        "username": "bifi",
        "message": "regnen tuts hier auch scho"
      },
      {
        "type": "message",
        "username": "maniac",
        "message": "und da die gelbe pollensiffe so widerständig is wirds auto net sauber sonder nur neu gemasert..."
      },
      {
        "type": "message",
        "username": "HAUSMARKE",
        "message": "jo die scheiß pollen sucken"
      },
      {
        "type": "message",
        "username": "T-wrk",
        "message": "polen? :D"
      },
      {
        "type": "message",
        "username": "HAUSMARKE",
        "message": "na die net"
      },
      {
        "type": "message",
        "username": "HAUSMARKE",
        "message": "pollenalarm = wenn das auto unter einer gelben schicht verschwunden ist - polenalarm = wenn das auto ganz verschwunden ist"
      },
      {
        "type": "misc",
        "text": "\n"
      }
    ]
  },
  {
    "date": {
      "fullDate": "22.05.2006 13:07",
      "date": "22.05.2006",
      "time": "13:07"
    },
    "id": "#42659",
    "content": [
      {
        "type": "message",
        "username": "Frischmilch",
        "message": "hab heute nen Fehler in der Matrix gesehen !!!"
      },
      {
        "type": "message",
        "username": "Frischmilch",
        "message": "wir laufen an nem Sportplatz vorbei ... 3 oder 4 Ghettokinder spielen Basketball"
      },
      {
        "type": "message",
        "username": "Frischmilch",
        "message": "und 3 sitzen am rand .. ich denk mir .. die drehen ne Tüte oder sowas .. ka"
      },
      {
        "type": "message",
        "username": "Frischmilch",
        "message": "als wir vorbei gelaufen sind hab ich gesehen dass die schach spielen !!!"
      },
      {
        "type": "message",
        "username": "Frischmilch",
        "message": "ich glaub das immernoch net..."
      }
    ]
  },
  {
    "date": {
      "fullDate": "22.05.2006 13:14",
      "date": "22.05.2006",
      "time": "13:14"
    },
    "id": "#42830",
    "content": [
      {
        "type": "message",
        "username": "slowrider",
        "message": "mir is was aufgefallen"
      },
      {
        "type": "message",
        "username": "slowrider",
        "message": "killerspiele sind schuld dass eltern gegen die spieleindustrie amok laufen"
      }
    ]
  },
  {
    "date": {
      "fullDate": "22.05.2006 13:14",
      "date": "22.05.2006",
      "time": "13:14"
    },
    "id": "#42836",
    "content": [
      {
        "type": "message",
        "username": "Larvi",
        "message": "kollege von mir hat mal ne zeit lang acid genommen und der war mal so drauf das er in den super markt gegangen ist und alle fischstäbchen gekauft hat und die dann in so nem grossen see bei uns freigelassen hat und dabei vor freude geheult hat ^^"
      }
    ]
  },
  {
    "date": {
      "fullDate": "22.05.2006 13:15",
      "date": "22.05.2006",
      "time": "13:15"
    },
    "id": "#42841",
    "content": [
      {
        "type": "message",
        "username": "u|",
        "message": "gegrillt"
      },
      {
        "type": "message",
        "username": "u|",
        "message": "hab 1.5gb fleisch gegessen"
      },
      {
        "type": "message",
        "username": "u|",
        "message": "kg"
      },
      {
        "type": "message",
        "username": "u|",
        "message": "lol"
      },
      {
        "type": "message",
        "username": "|Azrael|",
        "message": "LOL :D"
      }
    ]
  },
  {
    "date": {
      "fullDate": "22.05.2006 23:13",
      "date": "22.05.2006",
      "time": "23:13"
    },
    "id": "#42915",
    "content": [
      {
        "type": "message",
        "username": "Savio",
        "message": "Ich putz mir meine Nase zu hause IMMER mit Klopapier!"
      },
      {
        "type": "message",
        "username": "David",
        "message": "Du bist ja auch 'n Arschgesicht! :-D"
      },
      {
        "type": "message",
        "username": "Savio",
        "message": ":-\\ ha-ha"
      }
    ]
  },
  {
    "date": {
      "fullDate": "22.05.2006 23:33",
      "date": "22.05.2006",
      "time": "23:33"
    },
    "id": "#42908",
    "content": [
      {
        "type": "message",
        "username": "wilson",
        "message": "bestrafe mich!"
      },
      {
        "type": "message",
        "username": "wilson",
        "message": "gib mir tiernamen"
      },
      {
        "type": "message",
        "username": "PeaceKruemmel",
        "message": "du schmetterling"
      },
      {
        "type": "message",
        "username": "wilson",
        "message": "gib mir böse tiernamen"
      },
      {
        "type": "message",
        "username": "PeaceKruemmel",
        "message": "du böser schmetterling"
      }
    ]
  },
  {
    "date": {
      "fullDate": "22.05.2006 23:37",
      "date": "22.05.2006",
      "time": "23:37"
    },
    "id": "#43089",
    "content": [
      {
        "type": "message",
        "username": "psyc0wbiatch",
        "message": "n1.."
      },
      {
        "type": "message",
        "username": "sucks",
        "message": "was los?"
      },
      {
        "type": "message",
        "username": "psyc0wbiatch",
        "message": "gerade anruf von nem bekannten bekommen.. spym3n1 ist in der Psychatrie.."
      },
      {
        "type": "message",
        "username": "sucks",
        "message": "whut?"
      },
      {
        "type": "message",
        "username": "psyc0wbiatch",
        "message": "ja, er hat sich pilze gefressen, und ist dann nackt mit einer kerze in der hand durch die stadt gelaufen, weil er angst hatte das die eiskönigin ihn holt..."
      },
      {
        "type": "message",
        "username": "sucks",
        "message": "omg"
      }
    ]
  },
  {
    "date": {
      "fullDate": "23.05.2006 08:57",
      "date": "23.05.2006",
      "time": "08:57"
    },
    "id": "#43181",
    "content": [
      {
        "type": "message",
        "username": "Andruccio",
        "message": "ey...an muttertag laufen se alle mit blumen rum,die männer"
      },
      {
        "type": "message",
        "username": "Andruccio",
        "message": "aber an vatertag läuft nich eine frau mitm kasten bier rum!"
      }
    ]
  },
  {
    "date": {
      "fullDate": "25.05.2006 09:57",
      "date": "25.05.2006",
      "time": "09:57"
    },
    "id": "#43220",
    "content": [
      {
        "type": "message",
        "username": "SmokeyMcPot",
        "message": "FUCCCCCK!!!"
      },
      {
        "type": "message",
        "username": "ThorstenE",
        "message": "WAAAAASSS???"
      },
      {
        "type": "message",
        "username": "SmokeyMcPot",
        "message": "mir ist was ganz beschissenes passiert letzte nacht =((("
      },
      {
        "type": "message",
        "username": "ThorstenE",
        "message": "ja mir auch"
      },
      {
        "type": "message",
        "username": "SmokeyMcPot",
        "message": "Du kennst meine p0rn Sammlung... ich wollte sie mir mal wieder komplett rein ziehn"
      },
      {
        "type": "message",
        "username": "SmokeyMcPot",
        "message": "Und du kennst ja auch meine Kopfhörer, die fetten teile..."
      },
      {
        "type": "message",
        "username": "ThorstenE",
        "message": "Jo, nach meiner EmpfehlungDa kommt das stöhnen richtig gut *g*"
      },
      {
        "type": "message",
        "username": "SmokeyMcPot",
        "message": "maul jetzt!"
      },
      {
        "type": "message",
        "username": "SmokeyMcPot",
        "message": "ich also kopfhörer auf, und die vids angeschaut... shit"
      },
      {
        "type": "message",
        "username": "SmokeyMcPot",
        "message": "auf einmal steht mein Stiefvater in slips vor der Tür mit nem aggro gsicht und fuchtelt wild mit den armen rum"
      },
      {
        "type": "message",
        "username": "ThorstenE",
        "message": "was, wtf why?"
      },
      {
        "type": "message",
        "username": "SmokeyMcPot",
        "message": "ja pass auf"
      },
      {
        "type": "message",
        "username": "SmokeyMcPot",
        "message": "Ich nehm die kopfhörer ab und er motzt mich an"
      },
      {
        "type": "message",
        "username": "SmokeyMcPot",
        "message": "in meiner geilheit hab ich vergessen die Boxen aus zu machen =((("
      },
      {
        "type": "message",
        "username": "ThorstenE",
        "message": "ich glaub ich weis jetzt was passiert"
      },
      {
        "type": "message",
        "username": "ThorstenE",
        "message": "jetzt red kein scheiss, serious?"
      },
      {
        "type": "message",
        "username": "SmokeyMcPot",
        "message": "schnauze man, die sache ist mir so peinlich, und ich weiß nicht mal was peinlicher war... das gestöhne im kompletten haus, oder mein stiefvater in slips"
      },
      {
        "type": "message",
        "username": "ThorstenE",
        "message": "du bist so ein opfer :&gt;"
      },
      {
        "type": "message",
        "username": "SmokeyMcPot",
        "message": "aber hey, das gespräch hat nie statt gefunden!"
      },
      {
        "type": "message",
        "username": "SmokeyMcPot",
        "message": "halts maul jetzt!"
      },
      {
        "type": "message",
        "username": "ThorstenE",
        "message": "ja klar, wozu hat man den freunde *g*"
      }
    ]
  },
  {
    "date": {
      "fullDate": "25.05.2006 10:06",
      "date": "25.05.2006",
      "time": "10:06"
    },
    "id": "#43251",
    "content": [
      {
        "type": "message",
        "username": "faithless",
        "message": "meine religions lehrerin hält mich für rassistisch"
      },
      {
        "type": "message",
        "username": "freedom call",
        "message": "?"
      },
      {
        "type": "message",
        "username": "faithless",
        "message": "dabei hab ich mich sogar für die eingesetzt!"
      },
      {
        "type": "message",
        "username": "freedom call",
        "message": "was haste denn gemacht?"
      },
      {
        "type": "message",
        "username": "faithless",
        "message": "sie fragte ob jemand nen schwarzen stift für sie hätte"
      },
      {
        "type": "message",
        "username": "faithless",
        "message": "da meinte ich: DAS HEISST AFRO-AMERIAKISCHER STIFT!!"
      }
    ]
  },
  {
    "date": {
      "fullDate": "25.05.2006 10:54",
      "date": "25.05.2006",
      "time": "10:54"
    },
    "id": "#43268",
    "content": [
      {
        "type": "message",
        "username": "Impi^online",
        "message": "so, bett ist gemacht"
      },
      {
        "type": "message",
        "username": "Impi^online",
        "message": "freundin kommt gleich vorbei :&gt;"
      },
      {
        "type": "message",
        "username": "envieh",
        "message": "du machst dein bett?"
      },
      {
        "type": "message",
        "username": "Impi^online",
        "message": "ja nur wenn sie kommt"
      },
      {
        "type": "message",
        "username": "envieh",
        "message": "ich hab das nie gemacht bevor meine ex kam, bevor sie gegangen is hat sie es dann gemacht"
      },
      {
        "type": "message",
        "username": "Impi^online",
        "message": "darum wirds auch deine ex sein ^^"
      }
    ]
  },
  {
    "date": {
      "fullDate": "25.05.2006 12:40",
      "date": "25.05.2006",
      "time": "12:40"
    },
    "id": "#43252",
    "content": [
      {
        "type": "message",
        "username": "sacto",
        "message": "Lass mich in Ruhe!! Das einzige was du von mir bekommen kannst ist ne Gürtelrose!!"
      },
      {
        "type": "message",
        "username": "xTear",
        "message": "Ach das ist ja lieb von dir :) *smile*"
      },
      {
        "type": "message",
        "username": "sacto",
        "message": "WTF??????"
      },
      {
        "type": "message",
        "username": "xTear",
        "message": "moment...du Arsch...ich hab bei Google nachgesehen,Gürtelrose ist ja gar keine Blume!!!!!"
      },
      {
        "type": "message",
        "username": "sacto",
        "message": "LOOOOOOOOOOOOOOOL"
      }
    ]
  },
  {
    "date": {
      "fullDate": "26.05.2006 10:36",
      "date": "26.05.2006",
      "time": "10:36"
    },
    "id": "#43324",
    "content": [
      {
        "type": "message",
        "username": "Savio",
        "message": "rofl ich grad im bus"
      },
      {
        "type": "message",
        "username": "David",
        "message": "wat denn"
      },
      {
        "type": "message",
        "username": "Savio",
        "message": "ich sitz so alleine im bus mit nem typen, der typ schläft vorne und ich sitz weiter hinten"
      },
      {
        "type": "message",
        "username": "Savio",
        "message": "dann drück ich so auf den knopf damit der bus hält"
      },
      {
        "type": "message",
        "username": "Savio",
        "message": "der bus hält dann so, und keiner steigt ein oder aus"
      },
      {
        "type": "message",
        "username": "Savio",
        "message": "ich bück mich so hinter den sitz, damit der mich nich sieht, dann guckt der so in bus rein und sieht den typen pennen und denkt der verarscht den :D :D"
      },
      {
        "type": "message",
        "username": "Savio",
        "message": "der steht so auf, geht zu dem typen und schreit: \"Willst du mich verarschen!!!!\""
      },
      {
        "type": "message",
        "username": "Savio",
        "message": "der typ steht nur auf und is ausm bus gerannt :D :D"
      },
      {
        "type": "misc",
        "text": "\n"
      }
    ]
  },
  {
    "date": {
      "fullDate": "26.05.2006 10:46",
      "date": "26.05.2006",
      "time": "10:46"
    },
    "id": "#43423",
    "content": [
      {
        "type": "message",
        "username": "And1``",
        "message": "oh fuck.. mein zahnarzt meint ich soll inne tüte kacken weil ich ne goldplombe runtergeschluckt hab"
      }
    ]
  },
  {
    "date": {
      "fullDate": "26.05.2006 10:46",
      "date": "26.05.2006",
      "time": "10:46"
    },
    "id": "#43425",
    "content": [
      {
        "type": "message",
        "username": "|Berti|",
        "message": "War gerade im Supermarkt sehr lol!"
      },
      {
        "type": "message",
        "username": "|Berti|",
        "message": "An der Kasse sass nen recht junger Türke... 16 oder so... Jobben halt"
      },
      {
        "type": "message",
        "username": "|Berti|",
        "message": "Irgendeine ältere Türkin redet ihn ca. 1 min auf Türkisch voll..."
      },
      {
        "type": "message",
        "username": "|Berti|",
        "message": "Er zieht alles über den Scanner... nach ner guten Minute dann \"Ich spreche kein Türkisch\" ^^"
      }
    ]
  },
  {
    "date": {
      "fullDate": "26.05.2006 10:49",
      "date": "26.05.2006",
      "time": "10:49"
    },
    "id": "#43481",
    "content": [
      {
        "type": "message",
        "username": "benni",
        "message": "ey du wirst ned glauben was heut in der arbeit war"
      },
      {
        "type": "message",
        "username": "grigre",
        "message": "hö? "
      },
      {
        "type": "message",
        "username": "benni",
        "message": "wir haben zZ so ne doofe azubi-tusse in der abteilung, so richtig blond und dumm :D."
      },
      {
        "type": "message",
        "username": "grigre",
        "message": "kk"
      },
      {
        "type": "message",
        "username": "benni",
        "message": "die war heut bei den letzten im büro dabei und wird halt so abends gefragt: kannst du bitte die PCs herunterfahren? und was macht sie? geht zum ersten pc hin, baut ihn komplett ab, stellt das zeugs auf nen wagen und fährt ihn im fahrstuhl herunter ins erdgeschoss ^^"
      },
      {
        "type": "message",
        "username": "grigre",
        "message": "LOL"
      },
      {
        "type": "message",
        "username": "benni",
        "message": "das gesicht vom ausbildungschef hättest du sehen müssen, göttlich!"
      }
    ]
  },
  {
    "date": {
      "fullDate": "26.05.2006 10:50",
      "date": "26.05.2006",
      "time": "10:50"
    },
    "id": "#43491",
    "content": [
      {
        "type": "message",
        "username": "Phil",
        "message": "Meiner Mutter schafft mich..das ist so krass , ich glaub ich bring mich um !"
      },
      {
        "type": "message",
        "username": "Ingo",
        "message": "ROFL wasn jetzt schon wieder?"
      },
      {
        "type": "message",
        "username": "Phil",
        "message": "Wir hattens von Sexualleben und da fragt sie ich \" Meinst du ich hab kein Sexualleben ? \" ."
      },
      {
        "type": "message",
        "username": "Ingo",
        "message": "themen die die welt bewegen"
      },
      {
        "type": "message",
        "username": "Phil",
        "message": "ja aber es kam noch krasser , ich so \" ich hab zumindest lang kein kerl mehr bei uns gesehen \""
      },
      {
        "type": "message",
        "username": "Ingo",
        "message": "..."
      },
      {
        "type": "message",
        "username": "Phil",
        "message": "und sie so \" Ich hab 10 gesunde Finger ... \""
      },
      {
        "type": "message",
        "username": "Ingo",
        "message": "WÄÄÄÄÄÄÄÄH ich geb ihr nie mehr die hand..."
      }
    ]
  }
]